SunFounder_Emo/__init__.py
SunFounder_Emo/emo.py
SunFounder_Emo/emo_maps.py
SunFounder_Emo-1.1.0.dist-info/DESCRIPTION.rst
SunFounder_Emo-1.1.0.dist-info/METADATA
SunFounder_Emo-1.1.0.dist-info/RECORD
SunFounder_Emo-1.1.0.dist-info/WHEEL
SunFounder_Emo-1.1.0.dist-info/entry_points.txt
SunFounder_Emo-1.1.0.dist-info/metadata.json
SunFounder_Emo-1.1.0.dist-info/top_level.txt
