Metadata-Version: 2.0
Name: SunFounder-Emo
Version: 1.1.0
Summary: The class for SunFounder Emo
Home-page: https://github.com/sunfounder/SunFounder_Emo
Author: SunFounder
Author-email: service@sunfounder.com
License: GNU
Requires-Dist: spidev
